odoo/addons/sale_generator/README.rst
odoo/addons/sale_generator/__init__.py
odoo/addons/sale_generator/__manifest__.py
odoo/addons/sale_generator/data/data.xml
odoo/addons/sale_generator/i18n/de.po
odoo/addons/sale_generator/i18n/fr.po
odoo/addons/sale_generator/i18n/sale_generator.pot
odoo/addons/sale_generator/models/__init__.py
odoo/addons/sale_generator/models/partner.py
odoo/addons/sale_generator/models/sale_generator.py
odoo/addons/sale_generator/models/sale_order.py
odoo/addons/sale_generator/readme/CONTRIBUTORS.rst
odoo/addons/sale_generator/readme/DESCRIPTION.rst
odoo/addons/sale_generator/readme/USAGE.rst
odoo/addons/sale_generator/security/ir.model.access.csv
odoo/addons/sale_generator/security/ir_rule.xml
odoo/addons/sale_generator/static/description/icon.png
odoo/addons/sale_generator/static/description/index.html
odoo/addons/sale_generator/static/img/sale_gen_tmpl.png
odoo/addons/sale_generator/static/img/sale_generator.png
odoo/addons/sale_generator/tests/__init__.py
odoo/addons/sale_generator/tests/test_sale_generator.py
odoo/addons/sale_generator/views/generator_view.xml
odoo/addons/sale_generator/views/partner_view.xml
odoo/addons/sale_generator/views/sale_order_view.xml
odoo12_addon_sale_generator-12.0.1.0.2.dist-info/METADATA
odoo12_addon_sale_generator-12.0.1.0.2.dist-info/WHEEL
odoo12_addon_sale_generator-12.0.1.0.2.dist-info/top_level.txt
odoo12_addon_sale_generator-12.0.1.0.2.dist-info/RECORD
